concil/__init__.py
concil/cli.py
concil/concil_join.py
concil/concil_run.py
concil/cosign.py
concil/dockerhub.py
concil/image.py
concil/notary.py
concil/oci_spec.py
concil/run.py
concil/store.py
concil/streams.py
concil/squashfs/__init__.py
concil/squashfs/tar2squashfs.py
concil-1.0.0.dist-info/licenses/LICENSE
concil-1.0.0.dist-info/METADATA
concil-1.0.0.dist-info/WHEEL
concil-1.0.0.dist-info/entry_points.txt
concil-1.0.0.dist-info/top_level.txt
concil-1.0.0.dist-info/RECORD
